<?xml version="1.0" encoding="UTF-8"?>
<PublicationDelivery version="1.09:FR-NETEX_HORAIRE-2.1-1.0" xmlns="http://www.netex.org.uk/netex" xmlns:core="http://www.govtalk.gov.uk/core" xmlns:gml="http://www.opengis.net/gml/3.2" xmlns:ifopt="http://www.ifopt.org.uk/ifopt" xmlns:siri="http://www.siri.org.uk/siri" xmlns:xlink="http://www.w3.org/1999/xlink" xmlns:xsi="http://www.w3.org/2001/XMLSchema-instance" xsi:schemaLocation="http://www.netex.org.uk/netex">
	<PublicationTimestamp>2022-08-27T09:10:29+00:00</PublicationTimestamp>
	<ParticipantRef>transport.data.gouv.fr</ParticipantRef>
	<dataObjects>
		<GeneralFrame id="FR:GeneralFrame:NETEX_HORAIRE:" version="any">
			<members>
				<Route id="FR:Route:74:" version="any">
					<Name>COLL. LA RIVE - LAUMIERE</Name>
					<Distance>0</Distance>
					<LineRef ref="FR:Line:74:">
					</LineRef>
					<DirectionType>inbound</DirectionType>
					<pointsInSequence>
						<PointOnRoute id="FR:PointOnRoute:74_1:" order="1" version="any">
							<RoutePointRef ref="FR:RoutePoint:74_1:">
							</RoutePointRef>
						</PointOnRoute>
						<PointOnRoute id="FR:PointOnRoute:74_2:" order="2" version="any">
							<RoutePointRef ref="FR:RoutePoint:74_2:">
							</RoutePointRef>
						</PointOnRoute>
						<PointOnRoute id="FR:PointOnRoute:74_3:" order="3" version="any">
							<RoutePointRef ref="FR:RoutePoint:74_3:">
							</RoutePointRef>
						</PointOnRoute>
						<PointOnRoute id="FR:PointOnRoute:74_4:" order="4" version="any">
							<RoutePointRef ref="FR:RoutePoint:74_4:">
							</RoutePointRef>
						</PointOnRoute>
						<PointOnRoute id="FR:PointOnRoute:74_5:" order="5" version="any">
							<RoutePointRef ref="FR:RoutePoint:74_5:">
							</RoutePointRef>
						</PointOnRoute>
						<PointOnRoute id="FR:PointOnRoute:74_6:" order="6" version="any">
							<RoutePointRef ref="FR:RoutePoint:74_6:">
							</RoutePointRef>
						</PointOnRoute>
						<PointOnRoute id="FR:PointOnRoute:74_7:" order="7" version="any">
							<RoutePointRef ref="FR:RoutePoint:74_7:">
							</RoutePointRef>
						</PointOnRoute>
						<PointOnRoute id="FR:PointOnRoute:74_8:" order="8" version="any">
							<RoutePointRef ref="FR:RoutePoint:74_8:">
							</RoutePointRef>
						</PointOnRoute>
						<PointOnRoute id="FR:PointOnRoute:74_9:" order="9" version="any">
							<RoutePointRef ref="FR:RoutePoint:74_9:">
							</RoutePointRef>
						</PointOnRoute>
						<PointOnRoute id="FR:PointOnRoute:74_10:" order="10" version="any">
							<RoutePointRef ref="FR:RoutePoint:74_10:">
							</RoutePointRef>
						</PointOnRoute>
						<PointOnRoute id="FR:PointOnRoute:74_11:" order="11" version="any">
							<RoutePointRef ref="FR:RoutePoint:74_11:">
							</RoutePointRef>
						</PointOnRoute>
					</pointsInSequence>
				</Route>
				<Route id="FR:Route:74_R:" version="any">
					<Name>LAUMIERE - COLL. LA RIVE</Name>
					<Distance>0</Distance>
					<LineRef ref="FR:Line:74:">
					</LineRef>
					<DirectionType>outbound</DirectionType>
					<pointsInSequence>
						<PointOnRoute id="FR:PointOnRoute:74_R_1:" order="1" version="any">
							<RoutePointRef ref="FR:RoutePoint:74_R_1:">
							</RoutePointRef>
						</PointOnRoute>
						<PointOnRoute id="FR:PointOnRoute:74_R_2:" order="2" version="any">
							<RoutePointRef ref="FR:RoutePoint:74_R_2:">
							</RoutePointRef>
						</PointOnRoute>
						<PointOnRoute id="FR:PointOnRoute:74_R_3:" order="3" version="any">
							<RoutePointRef ref="FR:RoutePoint:74_R_3:">
							</RoutePointRef>
						</PointOnRoute>
						<PointOnRoute id="FR:PointOnRoute:74_R_4:" order="4" version="any">
							<RoutePointRef ref="FR:RoutePoint:74_R_4:">
							</RoutePointRef>
						</PointOnRoute>
						<PointOnRoute id="FR:PointOnRoute:74_R_5:" order="5" version="any">
							<RoutePointRef ref="FR:RoutePoint:74_R_5:">
							</RoutePointRef>
						</PointOnRoute>
						<PointOnRoute id="FR:PointOnRoute:74_R_6:" order="6" version="any">
							<RoutePointRef ref="FR:RoutePoint:74_R_6:">
							</RoutePointRef>
						</PointOnRoute>
						<PointOnRoute id="FR:PointOnRoute:74_R_7:" order="7" version="any">
							<RoutePointRef ref="FR:RoutePoint:74_R_7:">
							</RoutePointRef>
						</PointOnRoute>
						<PointOnRoute id="FR:PointOnRoute:74_R_8:" order="8" version="any">
							<RoutePointRef ref="FR:RoutePoint:74_R_8:">
							</RoutePointRef>
						</PointOnRoute>
						<PointOnRoute id="FR:PointOnRoute:74_R_9:" order="9" version="any">
							<RoutePointRef ref="FR:RoutePoint:74_R_9:">
							</RoutePointRef>
						</PointOnRoute>
						<PointOnRoute id="FR:PointOnRoute:74_R_10:" order="10" version="any">
							<RoutePointRef ref="FR:RoutePoint:74_R_10:">
							</RoutePointRef>
						</PointOnRoute>
					</pointsInSequence>
				</Route>
				<RoutePoint id="FR:RoutePoint:74_1:" version="any">
					<Location>
						<gml:pos srsName="EPSG:2154">798540.1761722276 6478616.127785353</gml:pos>
					</Location>
				</RoutePoint>
				<RoutePoint id="FR:RoutePoint:74_2:" version="any">
					<Location>
						<gml:pos srsName="EPSG:2154">798593.8119210455 6478931.386345713</gml:pos>
					</Location>
				</RoutePoint>
				<RoutePoint id="FR:RoutePoint:74_3:" version="any">
					<Location>
						<gml:pos srsName="EPSG:2154">798925.5638291343 6479172.344039652</gml:pos>
					</Location>
				</RoutePoint>
				<RoutePoint id="FR:RoutePoint:74_4:" version="any">
					<Location>
						<gml:pos srsName="EPSG:2154">799169.4572889765 6479303.149241597</gml:pos>
					</Location>
				</RoutePoint>
				<RoutePoint id="FR:RoutePoint:74_5:" version="any">
					<Location>
						<gml:pos srsName="EPSG:2154">799476.5412721827 6479110.708212029</gml:pos>
					</Location>
				</RoutePoint>
				<RoutePoint id="FR:RoutePoint:74_6:" version="any">
					<Location>
						<gml:pos srsName="EPSG:2154">799748.4723093894 6478896.586065757</gml:pos>
					</Location>
				</RoutePoint>
				<RoutePoint id="FR:RoutePoint:74_7:" version="any">
					<Location>
						<gml:pos srsName="EPSG:2154">800298.7094913464 6478982.822661922</gml:pos>
					</Location>
				</RoutePoint>
				<RoutePoint id="FR:RoutePoint:74_8:" version="any">
					<Location>
						<gml:pos srsName="EPSG:2154">800635.3633463951 6479212.748154123</gml:pos>
					</Location>
				</RoutePoint>
				<RoutePoint id="FR:RoutePoint:74_9:" version="any">
					<Location>
						<gml:pos srsName="EPSG:2154">800977.9814578076 6479556.520036937</gml:pos>
					</Location>
				</RoutePoint>
				<RoutePoint id="FR:RoutePoint:74_10:" version="any">
					<Location>
						<gml:pos srsName="EPSG:2154">801196.2575316987 6479729.504995924</gml:pos>
					</Location>
				</RoutePoint>
				<RoutePoint id="FR:RoutePoint:74_11:" version="any">
					<Location>
						<gml:pos srsName="EPSG:2154">801409.9675937778 6480070.377324447</gml:pos>
					</Location>
				</RoutePoint>
				<RoutePoint id="FR:RoutePoint:74_R_1:" version="any">
					<Location>
						<gml:pos srsName="EPSG:2154">801396.8612556218 6480056.501467825</gml:pos>
					</Location>
				</RoutePoint>
				<RoutePoint id="FR:RoutePoint:74_R_2:" version="any">
					<Location>
						<gml:pos srsName="EPSG:2154">801156.075501226 6479703.870340705</gml:pos>
					</Location>
				</RoutePoint>
				<RoutePoint id="FR:RoutePoint:74_R_3:" version="any">
					<Location>
						<gml:pos srsName="EPSG:2154">800973.003331934 6479558.560591281</gml:pos>
					</Location>
				</RoutePoint>
				<RoutePoint id="FR:RoutePoint:74_R_4:" version="any">
					<Location>
						<gml:pos srsName="EPSG:2154">800614.3583150377 6479209.929576835</gml:pos>
					</Location>
				</RoutePoint>
				<RoutePoint id="FR:RoutePoint:74_R_5:" version="any">
					<Location>
						<gml:pos srsName="EPSG:2154">800291.3168343081 6478935.927971907</gml:pos>
					</Location>
				</RoutePoint>
				<RoutePoint id="FR:RoutePoint:74_R_6:" version="any">
					<Location>
						<gml:pos srsName="EPSG:2154">799742.5546532453 6478905.628284233</gml:pos>
					</Location>
				</RoutePoint>
				<RoutePoint id="FR:RoutePoint:74_R_7:" version="any">
					<Location>
						<gml:pos srsName="EPSG:2154">799481.5788876159 6479115.660842594</gml:pos>
					</Location>
				</RoutePoint>
				<RoutePoint id="FR:RoutePoint:74_R_8:" version="any">
					<Location>
						<gml:pos srsName="EPSG:2154">798901.5702315338 6479170.549954971</gml:pos>
					</Location>
				</RoutePoint>
				<RoutePoint id="FR:RoutePoint:74_R_9:" version="any">
					<Location>
						<gml:pos srsName="EPSG:2154">798583.2607733499 6478865.535657484</gml:pos>
					</Location>
				</RoutePoint>
				<RoutePoint id="FR:RoutePoint:74_R_10:" version="any">
					<Location>
						<gml:pos srsName="EPSG:2154">798512.0335122307 6478596.385237019</gml:pos>
					</Location>
				</RoutePoint>
				<ServiceJourneyPattern id="FR:ServiceJourneyPattern:38313:" version="any">
					<Distance>0</Distance>
					<RouteRef ref="FR:Route:74:">
					</RouteRef>
					<pointsInSequence>
						<StopPointInJourneyPattern id="FR:StopPointInJourneyPattern:38313_1:" order="2" version="any">
							<ScheduledStopPointRef ref="FR:ScheduledStopPoint:38313_1:">
							</ScheduledStopPointRef>
							<ForAlighting>false</ForAlighting>
							<ForBoarding>true</ForBoarding>
						</StopPointInJourneyPattern>
						<StopPointInJourneyPattern id="FR:StopPointInJourneyPattern:38313_2:" order="3" version="any">
							<ScheduledStopPointRef ref="FR:ScheduledStopPoint:38313_2:">
							</ScheduledStopPointRef>
							<ForAlighting>true</ForAlighting>
							<ForBoarding>true</ForBoarding>
						</StopPointInJourneyPattern>
						<StopPointInJourneyPattern id="FR:StopPointInJourneyPattern:38313_3:" order="4" version="any">
							<ScheduledStopPointRef ref="FR:ScheduledStopPoint:38313_3:">
							</ScheduledStopPointRef>
							<ForAlighting>true</ForAlighting>
							<ForBoarding>true</ForBoarding>
						</StopPointInJourneyPattern>
						<StopPointInJourneyPattern id="FR:StopPointInJourneyPattern:38313_4:" order="5" version="any">
							<ScheduledStopPointRef ref="FR:ScheduledStopPoint:38313_4:">
							</ScheduledStopPointRef>
							<ForAlighting>true</ForAlighting>
							<ForBoarding>true</ForBoarding>
						</StopPointInJourneyPattern>
						<StopPointInJourneyPattern id="FR:StopPointInJourneyPattern:38313_5:" order="6" version="any">
							<ScheduledStopPointRef ref="FR:ScheduledStopPoint:38313_5:">
							</ScheduledStopPointRef>
							<ForAlighting>true</ForAlighting>
							<ForBoarding>true</ForBoarding>
						</StopPointInJourneyPattern>
						<StopPointInJourneyPattern id="FR:StopPointInJourneyPattern:38313_6:" order="7" version="any">
							<ScheduledStopPointRef ref="FR:ScheduledStopPoint:38313_6:">
							</ScheduledStopPointRef>
							<ForAlighting>true</ForAlighting>
							<ForBoarding>true</ForBoarding>
						</StopPointInJourneyPattern>
						<StopPointInJourneyPattern id="FR:StopPointInJourneyPattern:38313_7:" order="8" version="any">
							<ScheduledStopPointRef ref="FR:ScheduledStopPoint:38313_7:">
							</ScheduledStopPointRef>
							<ForAlighting>true</ForAlighting>
							<ForBoarding>true</ForBoarding>
						</StopPointInJourneyPattern>
						<StopPointInJourneyPattern id="FR:StopPointInJourneyPattern:38313_8:" order="9" version="any">
							<ScheduledStopPointRef ref="FR:ScheduledStopPoint:38313_8:">
							</ScheduledStopPointRef>
							<ForAlighting>true</ForAlighting>
							<ForBoarding>true</ForBoarding>
						</StopPointInJourneyPattern>
						<StopPointInJourneyPattern id="FR:StopPointInJourneyPattern:38313_9:" order="10" version="any">
							<ScheduledStopPointRef ref="FR:ScheduledStopPoint:38313_9:">
							</ScheduledStopPointRef>
							<ForAlighting>true</ForAlighting>
							<ForBoarding>true</ForBoarding>
						</StopPointInJourneyPattern>
						<StopPointInJourneyPattern id="FR:StopPointInJourneyPattern:38313_10:" order="11" version="any">
							<ScheduledStopPointRef ref="FR:ScheduledStopPoint:38313_10:">
							</ScheduledStopPointRef>
							<ForAlighting>true</ForAlighting>
							<ForBoarding>true</ForBoarding>
						</StopPointInJourneyPattern>
						<StopPointInJourneyPattern id="FR:StopPointInJourneyPattern:38313_11:" order="12" version="any">
							<ScheduledStopPointRef ref="FR:ScheduledStopPoint:38313_11:">
							</ScheduledStopPointRef>
							<ForAlighting>true</ForAlighting>
							<ForBoarding>false</ForBoarding>
						</StopPointInJourneyPattern>
					</pointsInSequence>
				</ServiceJourneyPattern>
				<ServiceJourneyPattern id="FR:ServiceJourneyPattern:38316:" version="any">
					<Distance>0</Distance>
					<RouteRef ref="FR:Route:74_R:">
					</RouteRef>
					<pointsInSequence>
						<StopPointInJourneyPattern id="FR:StopPointInJourneyPattern:38316_1:" order="2" version="any">
							<ScheduledStopPointRef ref="FR:ScheduledStopPoint:38316_1:">
							</ScheduledStopPointRef>
							<ForAlighting>false</ForAlighting>
							<ForBoarding>true</ForBoarding>
						</StopPointInJourneyPattern>
						<StopPointInJourneyPattern id="FR:StopPointInJourneyPattern:38316_2:" order="3" version="any">
							<ScheduledStopPointRef ref="FR:ScheduledStopPoint:38316_2:">
							</ScheduledStopPointRef>
							<ForAlighting>true</ForAlighting>
							<ForBoarding>true</ForBoarding>
						</StopPointInJourneyPattern>
						<StopPointInJourneyPattern id="FR:StopPointInJourneyPattern:38316_3:" order="4" version="any">
							<ScheduledStopPointRef ref="FR:ScheduledStopPoint:38316_3:">
							</ScheduledStopPointRef>
							<ForAlighting>true</ForAlighting>
							<ForBoarding>true</ForBoarding>
						</StopPointInJourneyPattern>
						<StopPointInJourneyPattern id="FR:StopPointInJourneyPattern:38316_4:" order="5" version="any">
							<ScheduledStopPointRef ref="FR:ScheduledStopPoint:38316_4:">
							</ScheduledStopPointRef>
							<ForAlighting>true</ForAlighting>
							<ForBoarding>true</ForBoarding>
						</StopPointInJourneyPattern>
						<StopPointInJourneyPattern id="FR:StopPointInJourneyPattern:38316_5:" order="6" version="any">
							<ScheduledStopPointRef ref="FR:ScheduledStopPoint:38316_5:">
							</ScheduledStopPointRef>
							<ForAlighting>true</ForAlighting>
							<ForBoarding>true</ForBoarding>
						</StopPointInJourneyPattern>
						<StopPointInJourneyPattern id="FR:StopPointInJourneyPattern:38316_6:" order="7" version="any">
							<ScheduledStopPointRef ref="FR:ScheduledStopPoint:38316_6:">
							</ScheduledStopPointRef>
							<ForAlighting>true</ForAlighting>
							<ForBoarding>true</ForBoarding>
						</StopPointInJourneyPattern>
						<StopPointInJourneyPattern id="FR:StopPointInJourneyPattern:38316_7:" order="8" version="any">
							<ScheduledStopPointRef ref="FR:ScheduledStopPoint:38316_7:">
							</ScheduledStopPointRef>
							<ForAlighting>true</ForAlighting>
							<ForBoarding>true</ForBoarding>
						</StopPointInJourneyPattern>
						<StopPointInJourneyPattern id="FR:StopPointInJourneyPattern:38316_8:" order="9" version="any">
							<ScheduledStopPointRef ref="FR:ScheduledStopPoint:38316_8:">
							</ScheduledStopPointRef>
							<ForAlighting>true</ForAlighting>
							<ForBoarding>true</ForBoarding>
						</StopPointInJourneyPattern>
						<StopPointInJourneyPattern id="FR:StopPointInJourneyPattern:38316_9:" order="10" version="any">
							<ScheduledStopPointRef ref="FR:ScheduledStopPoint:38316_9:">
							</ScheduledStopPointRef>
							<ForAlighting>true</ForAlighting>
							<ForBoarding>true</ForBoarding>
						</StopPointInJourneyPattern>
						<StopPointInJourneyPattern id="FR:StopPointInJourneyPattern:38316_10:" order="11" version="any">
							<ScheduledStopPointRef ref="FR:ScheduledStopPoint:38316_10:">
							</ScheduledStopPointRef>
							<ForAlighting>true</ForAlighting>
							<ForBoarding>false</ForBoarding>
						</StopPointInJourneyPattern>
					</pointsInSequence>
				</ServiceJourneyPattern>
				<ScheduledStopPoint id="FR:ScheduledStopPoint:38313_1:" version="any">
					<Location>
						<gml:pos srsName="EPSG:2154">798540.1761722276 6478616.127785353</gml:pos>
					</Location>
				</ScheduledStopPoint>
				<ScheduledStopPoint id="FR:ScheduledStopPoint:38313_2:" version="any">
					<Location>
						<gml:pos srsName="EPSG:2154">798593.8119210455 6478931.386345713</gml:pos>
					</Location>
				</ScheduledStopPoint>
				<ScheduledStopPoint id="FR:ScheduledStopPoint:38313_3:" version="any">
					<Location>
						<gml:pos srsName="EPSG:2154">798925.5638291343 6479172.344039652</gml:pos>
					</Location>
				</ScheduledStopPoint>
				<ScheduledStopPoint id="FR:ScheduledStopPoint:38313_4:" version="any">
					<Location>
						<gml:pos srsName="EPSG:2154">799169.4572889765 6479303.149241597</gml:pos>
					</Location>
				</ScheduledStopPoint>
				<ScheduledStopPoint id="FR:ScheduledStopPoint:38313_5:" version="any">
					<Location>
						<gml:pos srsName="EPSG:2154">799476.5412721827 6479110.708212029</gml:pos>
					</Location>
				</ScheduledStopPoint>
				<ScheduledStopPoint id="FR:ScheduledStopPoint:38313_6:" version="any">
					<Location>
						<gml:pos srsName="EPSG:2154">799748.4723093894 6478896.586065757</gml:pos>
					</Location>
				</ScheduledStopPoint>
				<ScheduledStopPoint id="FR:ScheduledStopPoint:38313_7:" version="any">
					<Location>
						<gml:pos srsName="EPSG:2154">800298.7094913464 6478982.822661922</gml:pos>
					</Location>
				</ScheduledStopPoint>
				<ScheduledStopPoint id="FR:ScheduledStopPoint:38313_8:" version="any">
					<Location>
						<gml:pos srsName="EPSG:2154">800635.3633463951 6479212.748154123</gml:pos>
					</Location>
				</ScheduledStopPoint>
				<ScheduledStopPoint id="FR:ScheduledStopPoint:38313_9:" version="any">
					<Location>
						<gml:pos srsName="EPSG:2154">800977.9814578076 6479556.520036937</gml:pos>
					</Location>
				</ScheduledStopPoint>
				<ScheduledStopPoint id="FR:ScheduledStopPoint:38313_10:" version="any">
					<Location>
						<gml:pos srsName="EPSG:2154">801196.2575316987 6479729.504995924</gml:pos>
					</Location>
				</ScheduledStopPoint>
				<ScheduledStopPoint id="FR:ScheduledStopPoint:38313_11:" version="any">
					<Location>
						<gml:pos srsName="EPSG:2154">801409.9675937778 6480070.377324447</gml:pos>
					</Location>
				</ScheduledStopPoint>
				<ScheduledStopPoint id="FR:ScheduledStopPoint:38316_1:" version="any">
					<Location>
						<gml:pos srsName="EPSG:2154">801396.8612556218 6480056.501467825</gml:pos>
					</Location>
				</ScheduledStopPoint>
				<ScheduledStopPoint id="FR:ScheduledStopPoint:38316_2:" version="any">
					<Location>
						<gml:pos srsName="EPSG:2154">801156.075501226 6479703.870340705</gml:pos>
					</Location>
				</ScheduledStopPoint>
				<ScheduledStopPoint id="FR:ScheduledStopPoint:38316_3:" version="any">
					<Location>
						<gml:pos srsName="EPSG:2154">800973.003331934 6479558.560591281</gml:pos>
					</Location>
				</ScheduledStopPoint>
				<ScheduledStopPoint id="FR:ScheduledStopPoint:38316_4:" version="any">
					<Location>
						<gml:pos srsName="EPSG:2154">800614.3583150377 6479209.929576835</gml:pos>
					</Location>
				</ScheduledStopPoint>
				<ScheduledStopPoint id="FR:ScheduledStopPoint:38316_5:" version="any">
					<Location>
						<gml:pos srsName="EPSG:2154">800291.3168343081 6478935.927971907</gml:pos>
					</Location>
				</ScheduledStopPoint>
				<ScheduledStopPoint id="FR:ScheduledStopPoint:38316_6:" version="any">
					<Location>
						<gml:pos srsName="EPSG:2154">799742.5546532453 6478905.628284233</gml:pos>
					</Location>
				</ScheduledStopPoint>
				<ScheduledStopPoint id="FR:ScheduledStopPoint:38316_7:" version="any">
					<Location>
						<gml:pos srsName="EPSG:2154">799481.5788876159 6479115.660842594</gml:pos>
					</Location>
				</ScheduledStopPoint>
				<ScheduledStopPoint id="FR:ScheduledStopPoint:38316_8:" version="any">
					<Location>
						<gml:pos srsName="EPSG:2154">798901.5702315338 6479170.549954971</gml:pos>
					</Location>
				</ScheduledStopPoint>
				<ScheduledStopPoint id="FR:ScheduledStopPoint:38316_9:" version="any">
					<Location>
						<gml:pos srsName="EPSG:2154">798583.2607733499 6478865.535657484</gml:pos>
					</Location>
				</ScheduledStopPoint>
				<ScheduledStopPoint id="FR:ScheduledStopPoint:38316_10:" version="any">
					<Location>
						<gml:pos srsName="EPSG:2154">798512.0335122307 6478596.385237019</gml:pos>
					</Location>
				</ScheduledStopPoint>
				<PassengerStopAssignment id="FR:PassengerStopAssignment:38313_1:" order="2" version="any">
					<ScheduledStopPointRef ref="FR:ScheduledStopPoint:38313_1:">
					</ScheduledStopPointRef>
					<StopPlaceRef ref="FR:StopPlace:Navitia_198_bus:">
					</StopPlaceRef>
					<QuayRef ref="FR:Quay:198:">
					</QuayRef>
				</PassengerStopAssignment>
				<PassengerStopAssignment id="FR:PassengerStopAssignment:38313_2:" order="3" version="any">
					<ScheduledStopPointRef ref="FR:ScheduledStopPoint:38313_2:">
					</ScheduledStopPointRef>
					<StopPlaceRef ref="FR:StopPlace:Navitia_199_bus:">
					</StopPlaceRef>
					<QuayRef ref="FR:Quay:199:">
					</QuayRef>
				</PassengerStopAssignment>
				<PassengerStopAssignment id="FR:PassengerStopAssignment:38313_3:" order="4" version="any">
					<ScheduledStopPointRef ref="FR:ScheduledStopPoint:38313_3:">
					</ScheduledStopPointRef>
					<StopPlaceRef ref="FR:StopPlace:Navitia_230_bus:">
					</StopPlaceRef>
					<QuayRef ref="FR:Quay:230:">
					</QuayRef>
				</PassengerStopAssignment>
				<PassengerStopAssignment id="FR:PassengerStopAssignment:38313_4:" order="5" version="any">
					<ScheduledStopPointRef ref="FR:ScheduledStopPoint:38313_4:">
					</ScheduledStopPointRef>
					<StopPlaceRef ref="FR:StopPlace:Navitia_233_bus:">
					</StopPlaceRef>
					<QuayRef ref="FR:Quay:233:">
					</QuayRef>
				</PassengerStopAssignment>
				<PassengerStopAssignment id="FR:PassengerStopAssignment:38313_5:" order="6" version="any">
					<ScheduledStopPointRef ref="FR:ScheduledStopPoint:38313_5:">
					</ScheduledStopPointRef>
					<StopPlaceRef ref="FR:StopPlace:Navitia_2630_bus:">
					</StopPlaceRef>
					<QuayRef ref="FR:Quay:2630:">
					</QuayRef>
				</PassengerStopAssignment>
				<PassengerStopAssignment id="FR:PassengerStopAssignment:38313_6:" order="7" version="any">
					<ScheduledStopPointRef ref="FR:ScheduledStopPoint:38313_6:">
					</ScheduledStopPointRef>
					<StopPlaceRef ref="FR:StopPlace:Navitia_2632_bus:">
					</StopPlaceRef>
					<QuayRef ref="FR:Quay:2632:">
					</QuayRef>
				</PassengerStopAssignment>
				<PassengerStopAssignment id="FR:PassengerStopAssignment:38313_7:" order="8" version="any">
					<ScheduledStopPointRef ref="FR:ScheduledStopPoint:38313_7:">
					</ScheduledStopPointRef>
					<StopPlaceRef ref="FR:StopPlace:Navitia_2634_bus:">
					</StopPlaceRef>
					<QuayRef ref="FR:Quay:2634:">
					</QuayRef>
				</PassengerStopAssignment>
				<PassengerStopAssignment id="FR:PassengerStopAssignment:38313_8:" order="9" version="any">
					<ScheduledStopPointRef ref="FR:ScheduledStopPoint:38313_8:">
					</ScheduledStopPointRef>
					<StopPlaceRef ref="FR:StopPlace:Navitia_2638_bus:">
					</StopPlaceRef>
					<QuayRef ref="FR:Quay:2638:">
					</QuayRef>
				</PassengerStopAssignment>
				<PassengerStopAssignment id="FR:PassengerStopAssignment:38313_9:" order="10" version="any">
					<ScheduledStopPointRef ref="FR:ScheduledStopPoint:38313_9:">
					</ScheduledStopPointRef>
					<StopPlaceRef ref="FR:StopPlace:Navitia_2640_bus:">
					</StopPlaceRef>
					<QuayRef ref="FR:Quay:2640:">
					</QuayRef>
				</PassengerStopAssignment>
				<PassengerStopAssignment id="FR:PassengerStopAssignment:38313_10:" order="11" version="any">
					<ScheduledStopPointRef ref="FR:ScheduledStopPoint:38313_10:">
					</ScheduledStopPointRef>
					<StopPlaceRef ref="FR:StopPlace:Navitia_2643_bus:">
					</StopPlaceRef>
					<QuayRef ref="FR:Quay:2643:">
					</QuayRef>
				</PassengerStopAssignment>
				<PassengerStopAssignment id="FR:PassengerStopAssignment:38313_11:" order="12" version="any">
					<ScheduledStopPointRef ref="FR:ScheduledStopPoint:38313_11:">
					</ScheduledStopPointRef>
					<StopPlaceRef ref="FR:StopPlace:Navitia_2286_bus:">
					</StopPlaceRef>
					<QuayRef ref="FR:Quay:2286:">
					</QuayRef>
				</PassengerStopAssignment>
				<PassengerStopAssignment id="FR:PassengerStopAssignment:38316_1:" order="2" version="any">
					<ScheduledStopPointRef ref="FR:ScheduledStopPoint:38316_1:">
					</ScheduledStopPointRef>
					<StopPlaceRef ref="FR:StopPlace:Navitia_2285_bus:">
					</StopPlaceRef>
					<QuayRef ref="FR:Quay:2285:">
					</QuayRef>
				</PassengerStopAssignment>
				<PassengerStopAssignment id="FR:PassengerStopAssignment:38316_2:" order="3" version="any">
					<ScheduledStopPointRef ref="FR:ScheduledStopPoint:38316_2:">
					</ScheduledStopPointRef>
					<StopPlaceRef ref="FR:StopPlace:Navitia_2644_bus:">
					</StopPlaceRef>
					<QuayRef ref="FR:Quay:2644:">
					</QuayRef>
				</PassengerStopAssignment>
				<PassengerStopAssignment id="FR:PassengerStopAssignment:38316_3:" order="4" version="any">
					<ScheduledStopPointRef ref="FR:ScheduledStopPoint:38316_3:">
					</ScheduledStopPointRef>
					<StopPlaceRef ref="FR:StopPlace:Navitia_2641_bus:">
					</StopPlaceRef>
					<QuayRef ref="FR:Quay:2641:">
					</QuayRef>
				</PassengerStopAssignment>
				<PassengerStopAssignment id="FR:PassengerStopAssignment:38316_4:" order="5" version="any">
					<ScheduledStopPointRef ref="FR:ScheduledStopPoint:38316_4:">
					</ScheduledStopPointRef>
					<StopPlaceRef ref="FR:StopPlace:Navitia_2639_bus:">
					</StopPlaceRef>
					<QuayRef ref="FR:Quay:2639:">
					</QuayRef>
				</PassengerStopAssignment>
				<PassengerStopAssignment id="FR:PassengerStopAssignment:38316_5:" order="6" version="any">
					<ScheduledStopPointRef ref="FR:ScheduledStopPoint:38316_5:">
					</ScheduledStopPointRef>
					<StopPlaceRef ref="FR:StopPlace:Navitia_2635_bus:">
					</StopPlaceRef>
					<QuayRef ref="FR:Quay:2635:">
					</QuayRef>
				</PassengerStopAssignment>
				<PassengerStopAssignment id="FR:PassengerStopAssignment:38316_6:" order="7" version="any">
					<ScheduledStopPointRef ref="FR:ScheduledStopPoint:38316_6:">
					</ScheduledStopPointRef>
					<StopPlaceRef ref="FR:StopPlace:Navitia_2633_bus:">
					</StopPlaceRef>
					<QuayRef ref="FR:Quay:2633:">
					</QuayRef>
				</PassengerStopAssignment>
				<PassengerStopAssignment id="FR:PassengerStopAssignment:38316_7:" order="8" version="any">
					<ScheduledStopPointRef ref="FR:ScheduledStopPoint:38316_7:">
					</ScheduledStopPointRef>
					<StopPlaceRef ref="FR:StopPlace:Navitia_2631_bus:">
					</StopPlaceRef>
					<QuayRef ref="FR:Quay:2631:">
					</QuayRef>
				</PassengerStopAssignment>
				<PassengerStopAssignment id="FR:PassengerStopAssignment:38316_8:" order="9" version="any">
					<ScheduledStopPointRef ref="FR:ScheduledStopPoint:38316_8:">
					</ScheduledStopPointRef>
					<StopPlaceRef ref="FR:StopPlace:Navitia_229_bus:">
					</StopPlaceRef>
					<QuayRef ref="FR:Quay:229:">
					</QuayRef>
				</PassengerStopAssignment>
				<PassengerStopAssignment id="FR:PassengerStopAssignment:38316_9:" order="10" version="any">
					<ScheduledStopPointRef ref="FR:ScheduledStopPoint:38316_9:">
					</ScheduledStopPointRef>
					<StopPlaceRef ref="FR:StopPlace:Navitia_200_bus:">
					</StopPlaceRef>
					<QuayRef ref="FR:Quay:200:">
					</QuayRef>
				</PassengerStopAssignment>
				<PassengerStopAssignment id="FR:PassengerStopAssignment:38316_10:" order="11" version="any">
					<ScheduledStopPointRef ref="FR:ScheduledStopPoint:38316_10:">
					</ScheduledStopPointRef>
					<StopPlaceRef ref="FR:StopPlace:Navitia_195_bus:">
					</StopPlaceRef>
					<QuayRef ref="FR:Quay:195:">
					</QuayRef>
				</PassengerStopAssignment>
				<ServiceJourney id="FR:ServiceJourney:38313:" version="any">
					<dayTypes>
						<DayTypeRef ref="FR:DayType:H1-0-1-31:">
						</DayTypeRef>
					</dayTypes>
					<JourneyPatternRef ref="FR:ServiceJourneyPattern:38313:">
					</JourneyPatternRef>
					<OperatorRef ref="FR:Operator:1:">
					</OperatorRef>
					<passingTimes>
						<TimetabledPassingTime>
							<ArrivalTime>12:08:00</ArrivalTime>
							<ArrivalDayOffset>0</ArrivalDayOffset>
							<DepartureTime>12:08:00</DepartureTime>
							<DepartureDayOffset>0</DepartureDayOffset>
						</TimetabledPassingTime>
						<TimetabledPassingTime>
							<ArrivalTime>12:09:00</ArrivalTime>
							<ArrivalDayOffset>0</ArrivalDayOffset>
							<DepartureTime>12:09:00</DepartureTime>
							<DepartureDayOffset>0</DepartureDayOffset>
						</TimetabledPassingTime>
						<TimetabledPassingTime>
							<ArrivalTime>12:11:00</ArrivalTime>
							<ArrivalDayOffset>0</ArrivalDayOffset>
							<DepartureTime>12:11:00</DepartureTime>
							<DepartureDayOffset>0</DepartureDayOffset>
						</TimetabledPassingTime>
						<TimetabledPassingTime>
							<ArrivalTime>12:13:00</ArrivalTime>
							<ArrivalDayOffset>0</ArrivalDayOffset>
							<DepartureTime>12:13:00</DepartureTime>
							<DepartureDayOffset>0</DepartureDayOffset>
						</TimetabledPassingTime>
						<TimetabledPassingTime>
							<ArrivalTime>12:14:00</ArrivalTime>
							<ArrivalDayOffset>0</ArrivalDayOffset>
							<DepartureTime>12:14:00</DepartureTime>
							<DepartureDayOffset>0</DepartureDayOffset>
						</TimetabledPassingTime>
						<TimetabledPassingTime>
							<ArrivalTime>12:16:00</ArrivalTime>
							<ArrivalDayOffset>0</ArrivalDayOffset>
							<DepartureTime>12:16:00</DepartureTime>
							<DepartureDayOffset>0</DepartureDayOffset>
						</TimetabledPassingTime>
						<TimetabledPassingTime>
							<ArrivalTime>12:18:00</ArrivalTime>
							<ArrivalDayOffset>0</ArrivalDayOffset>
							<DepartureTime>12:18:00</DepartureTime>
							<DepartureDayOffset>0</DepartureDayOffset>
						</TimetabledPassingTime>
						<TimetabledPassingTime>
							<ArrivalTime>12:19:00</ArrivalTime>
							<ArrivalDayOffset>0</ArrivalDayOffset>
							<DepartureTime>12:19:00</DepartureTime>
							<DepartureDayOffset>0</DepartureDayOffset>
						</TimetabledPassingTime>
						<TimetabledPassingTime>
							<ArrivalTime>12:21:00</ArrivalTime>
							<ArrivalDayOffset>0</ArrivalDayOffset>
							<DepartureTime>12:21:00</DepartureTime>
							<DepartureDayOffset>0</DepartureDayOffset>
						</TimetabledPassingTime>
						<TimetabledPassingTime>
							<ArrivalTime>12:22:00</ArrivalTime>
							<ArrivalDayOffset>0</ArrivalDayOffset>
							<DepartureTime>12:22:00</DepartureTime>
							<DepartureDayOffset>0</DepartureDayOffset>
						</TimetabledPassingTime>
						<TimetabledPassingTime>
							<ArrivalTime>12:23:00</ArrivalTime>
							<ArrivalDayOffset>0</ArrivalDayOffset>
							<DepartureTime>12:23:00</DepartureTime>
							<DepartureDayOffset>0</DepartureDayOffset>
						</TimetabledPassingTime>
					</passingTimes>
				</ServiceJourney>
				<ServiceJourney id="FR:ServiceJourney:38314:" version="any">
					<dayTypes>
						<DayTypeRef ref="FR:DayType:H1-0-1-27:">
						</DayTypeRef>
					</dayTypes>
					<JourneyPatternRef ref="FR:ServiceJourneyPattern:38313:">
					</JourneyPatternRef>
					<OperatorRef ref="FR:Operator:1:">
					</OperatorRef>
					<passingTimes>
						<TimetabledPassingTime>
							<ArrivalTime>16:35:00</ArrivalTime>
							<ArrivalDayOffset>0</ArrivalDayOffset>
							<DepartureTime>16:35:00</DepartureTime>
							<DepartureDayOffset>0</DepartureDayOffset>
						</TimetabledPassingTime>
						<TimetabledPassingTime>
							<ArrivalTime>16:36:00</ArrivalTime>
							<ArrivalDayOffset>0</ArrivalDayOffset>
							<DepartureTime>16:36:00</DepartureTime>
							<DepartureDayOffset>0</DepartureDayOffset>
						</TimetabledPassingTime>
						<TimetabledPassingTime>
							<ArrivalTime>16:38:00</ArrivalTime>
							<ArrivalDayOffset>0</ArrivalDayOffset>
							<DepartureTime>16:38:00</DepartureTime>
							<DepartureDayOffset>0</DepartureDayOffset>
						</TimetabledPassingTime>
						<TimetabledPassingTime>
							<ArrivalTime>16:40:00</ArrivalTime>
							<ArrivalDayOffset>0</ArrivalDayOffset>
							<DepartureTime>16:40:00</DepartureTime>
							<DepartureDayOffset>0</DepartureDayOffset>
						</TimetabledPassingTime>
						<TimetabledPassingTime>
							<ArrivalTime>16:41:00</ArrivalTime>
							<ArrivalDayOffset>0</ArrivalDayOffset>
							<DepartureTime>16:41:00</DepartureTime>
							<DepartureDayOffset>0</DepartureDayOffset>
						</TimetabledPassingTime>
						<TimetabledPassingTime>
							<ArrivalTime>16:43:00</ArrivalTime>
							<ArrivalDayOffset>0</ArrivalDayOffset>
							<DepartureTime>16:43:00</DepartureTime>
							<DepartureDayOffset>0</DepartureDayOffset>
						</TimetabledPassingTime>
						<TimetabledPassingTime>
							<ArrivalTime>16:45:00</ArrivalTime>
							<ArrivalDayOffset>0</ArrivalDayOffset>
							<DepartureTime>16:45:00</DepartureTime>
							<DepartureDayOffset>0</DepartureDayOffset>
						</TimetabledPassingTime>
						<TimetabledPassingTime>
							<ArrivalTime>16:46:00</ArrivalTime>
							<ArrivalDayOffset>0</ArrivalDayOffset>
							<DepartureTime>16:46:00</DepartureTime>
							<DepartureDayOffset>0</DepartureDayOffset>
						</TimetabledPassingTime>
						<TimetabledPassingTime>
							<ArrivalTime>16:48:00</ArrivalTime>
							<ArrivalDayOffset>0</ArrivalDayOffset>
							<DepartureTime>16:48:00</DepartureTime>
							<DepartureDayOffset>0</DepartureDayOffset>
						</TimetabledPassingTime>
						<TimetabledPassingTime>
							<ArrivalTime>16:49:00</ArrivalTime>
							<ArrivalDayOffset>0</ArrivalDayOffset>
							<DepartureTime>16:49:00</DepartureTime>
							<DepartureDayOffset>0</DepartureDayOffset>
						</TimetabledPassingTime>
						<TimetabledPassingTime>
							<ArrivalTime>16:50:00</ArrivalTime>
							<ArrivalDayOffset>0</ArrivalDayOffset>
							<DepartureTime>16:50:00</DepartureTime>
							<DepartureDayOffset>0</DepartureDayOffset>
						</TimetabledPassingTime>
					</passingTimes>
				</ServiceJourney>
				<ServiceJourney id="FR:ServiceJourney:38315:" version="any">
					<dayTypes>
						<DayTypeRef ref="FR:DayType:H1-0-1-27:">
						</DayTypeRef>
					</dayTypes>
					<JourneyPatternRef ref="FR:ServiceJourneyPattern:38313:">
					</JourneyPatternRef>
					<OperatorRef ref="FR:Operator:1:">
					</OperatorRef>
					<passingTimes>
						<TimetabledPassingTime>
							<ArrivalTime>17:28:00</ArrivalTime>
							<ArrivalDayOffset>0</ArrivalDayOffset>
							<DepartureTime>17:28:00</DepartureTime>
							<DepartureDayOffset>0</DepartureDayOffset>
						</TimetabledPassingTime>
						<TimetabledPassingTime>
							<ArrivalTime>17:29:00</ArrivalTime>
							<ArrivalDayOffset>0</ArrivalDayOffset>
							<DepartureTime>17:29:00</DepartureTime>
							<DepartureDayOffset>0</DepartureDayOffset>
						</TimetabledPassingTime>
						<TimetabledPassingTime>
							<ArrivalTime>17:31:00</ArrivalTime>
							<ArrivalDayOffset>0</ArrivalDayOffset>
							<DepartureTime>17:31:00</DepartureTime>
							<DepartureDayOffset>0</DepartureDayOffset>
						</TimetabledPassingTime>
						<TimetabledPassingTime>
							<ArrivalTime>17:33:00</ArrivalTime>
							<ArrivalDayOffset>0</ArrivalDayOffset>
							<DepartureTime>17:33:00</DepartureTime>
							<DepartureDayOffset>0</DepartureDayOffset>
						</TimetabledPassingTime>
						<TimetabledPassingTime>
							<ArrivalTime>17:34:00</ArrivalTime>
							<ArrivalDayOffset>0</ArrivalDayOffset>
							<DepartureTime>17:34:00</DepartureTime>
							<DepartureDayOffset>0</DepartureDayOffset>
						</TimetabledPassingTime>
						<TimetabledPassingTime>
							<ArrivalTime>17:36:00</ArrivalTime>
							<ArrivalDayOffset>0</ArrivalDayOffset>
							<DepartureTime>17:36:00</DepartureTime>
							<DepartureDayOffset>0</DepartureDayOffset>
						</TimetabledPassingTime>
						<TimetabledPassingTime>
							<ArrivalTime>17:38:00</ArrivalTime>
							<ArrivalDayOffset>0</ArrivalDayOffset>
							<DepartureTime>17:38:00</DepartureTime>
							<DepartureDayOffset>0</DepartureDayOffset>
						</TimetabledPassingTime>
						<TimetabledPassingTime>
							<ArrivalTime>17:39:00</ArrivalTime>
							<ArrivalDayOffset>0</ArrivalDayOffset>
							<DepartureTime>17:39:00</DepartureTime>
							<DepartureDayOffset>0</DepartureDayOffset>
						</TimetabledPassingTime>
						<TimetabledPassingTime>
							<ArrivalTime>17:41:00</ArrivalTime>
							<ArrivalDayOffset>0</ArrivalDayOffset>
							<DepartureTime>17:41:00</DepartureTime>
							<DepartureDayOffset>0</DepartureDayOffset>
						</TimetabledPassingTime>
						<TimetabledPassingTime>
							<ArrivalTime>17:42:00</ArrivalTime>
							<ArrivalDayOffset>0</ArrivalDayOffset>
							<DepartureTime>17:42:00</DepartureTime>
							<DepartureDayOffset>0</DepartureDayOffset>
						</TimetabledPassingTime>
						<TimetabledPassingTime>
							<ArrivalTime>17:43:00</ArrivalTime>
							<ArrivalDayOffset>0</ArrivalDayOffset>
							<DepartureTime>17:43:00</DepartureTime>
							<DepartureDayOffset>0</DepartureDayOffset>
						</TimetabledPassingTime>
					</passingTimes>
				</ServiceJourney>
				<ServiceJourney id="FR:ServiceJourney:38316:" version="any">
					<dayTypes>
						<DayTypeRef ref="FR:DayType:H1-0-1-31:">
						</DayTypeRef>
					</dayTypes>
					<JourneyPatternRef ref="FR:ServiceJourneyPattern:38316:">
					</JourneyPatternRef>
					<OperatorRef ref="FR:Operator:1:">
					</OperatorRef>
					<passingTimes>
						<TimetabledPassingTime>
							<ArrivalTime>07:30:00</ArrivalTime>
							<ArrivalDayOffset>0</ArrivalDayOffset>
							<DepartureTime>07:30:00</DepartureTime>
							<DepartureDayOffset>0</DepartureDayOffset>
						</TimetabledPassingTime>
						<TimetabledPassingTime>
							<ArrivalTime>07:31:00</ArrivalTime>
							<ArrivalDayOffset>0</ArrivalDayOffset>
							<DepartureTime>07:31:00</DepartureTime>
							<DepartureDayOffset>0</DepartureDayOffset>
						</TimetabledPassingTime>
						<TimetabledPassingTime>
							<ArrivalTime>07:32:00</ArrivalTime>
							<ArrivalDayOffset>0</ArrivalDayOffset>
							<DepartureTime>07:32:00</DepartureTime>
							<DepartureDayOffset>0</DepartureDayOffset>
						</TimetabledPassingTime>
						<TimetabledPassingTime>
							<ArrivalTime>07:34:00</ArrivalTime>
							<ArrivalDayOffset>0</ArrivalDayOffset>
							<DepartureTime>07:34:00</DepartureTime>
							<DepartureDayOffset>0</DepartureDayOffset>
						</TimetabledPassingTime>
						<TimetabledPassingTime>
							<ArrivalTime>07:35:00</ArrivalTime>
							<ArrivalDayOffset>0</ArrivalDayOffset>
							<DepartureTime>07:35:00</DepartureTime>
							<DepartureDayOffset>0</DepartureDayOffset>
						</TimetabledPassingTime>
						<TimetabledPassingTime>
							<ArrivalTime>07:37:00</ArrivalTime>
							<ArrivalDayOffset>0</ArrivalDayOffset>
							<DepartureTime>07:37:00</DepartureTime>
							<DepartureDayOffset>0</DepartureDayOffset>
						</TimetabledPassingTime>
						<TimetabledPassingTime>
							<ArrivalTime>07:39:00</ArrivalTime>
							<ArrivalDayOffset>0</ArrivalDayOffset>
							<DepartureTime>07:39:00</DepartureTime>
							<DepartureDayOffset>0</DepartureDayOffset>
						</TimetabledPassingTime>
						<TimetabledPassingTime>
							<ArrivalTime>07:42:00</ArrivalTime>
							<ArrivalDayOffset>0</ArrivalDayOffset>
							<DepartureTime>07:42:00</DepartureTime>
							<DepartureDayOffset>0</DepartureDayOffset>
						</TimetabledPassingTime>
						<TimetabledPassingTime>
							<ArrivalTime>07:44:00</ArrivalTime>
							<ArrivalDayOffset>0</ArrivalDayOffset>
							<DepartureTime>07:44:00</DepartureTime>
							<DepartureDayOffset>0</DepartureDayOffset>
						</TimetabledPassingTime>
						<TimetabledPassingTime>
							<ArrivalTime>07:45:00</ArrivalTime>
							<ArrivalDayOffset>0</ArrivalDayOffset>
							<DepartureTime>07:45:00</DepartureTime>
							<DepartureDayOffset>0</DepartureDayOffset>
						</TimetabledPassingTime>
					</passingTimes>
				</ServiceJourney>
				<ServiceJourney id="FR:ServiceJourney:38317:" version="any">
					<dayTypes>
						<DayTypeRef ref="FR:DayType:H1-0-1-27:">
						</DayTypeRef>
					</dayTypes>
					<JourneyPatternRef ref="FR:ServiceJourneyPattern:38316:">
					</JourneyPatternRef>
					<OperatorRef ref="FR:Operator:1:">
					</OperatorRef>
					<passingTimes>
						<TimetabledPassingTime>
							<ArrivalTime>13:00:00</ArrivalTime>
							<ArrivalDayOffset>0</ArrivalDayOffset>
							<DepartureTime>13:00:00</DepartureTime>
							<DepartureDayOffset>0</DepartureDayOffset>
						</TimetabledPassingTime>
						<TimetabledPassingTime>
							<ArrivalTime>13:01:00</ArrivalTime>
							<ArrivalDayOffset>0</ArrivalDayOffset>
							<DepartureTime>13:01:00</DepartureTime>
							<DepartureDayOffset>0</DepartureDayOffset>
						</TimetabledPassingTime>
						<TimetabledPassingTime>
							<ArrivalTime>13:02:00</ArrivalTime>
							<ArrivalDayOffset>0</ArrivalDayOffset>
							<DepartureTime>13:02:00</DepartureTime>
							<DepartureDayOffset>0</DepartureDayOffset>
						</TimetabledPassingTime>
						<TimetabledPassingTime>
							<ArrivalTime>13:04:00</ArrivalTime>
							<ArrivalDayOffset>0</ArrivalDayOffset>
							<DepartureTime>13:04:00</DepartureTime>
							<DepartureDayOffset>0</DepartureDayOffset>
						</TimetabledPassingTime>
						<TimetabledPassingTime>
							<ArrivalTime>13:05:00</ArrivalTime>
							<ArrivalDayOffset>0</ArrivalDayOffset>
							<DepartureTime>13:05:00</DepartureTime>
							<DepartureDayOffset>0</DepartureDayOffset>
						</TimetabledPassingTime>
						<TimetabledPassingTime>
							<ArrivalTime>13:07:00</ArrivalTime>
							<ArrivalDayOffset>0</ArrivalDayOffset>
							<DepartureTime>13:07:00</DepartureTime>
							<DepartureDayOffset>0</DepartureDayOffset>
						</TimetabledPassingTime>
						<TimetabledPassingTime>
							<ArrivalTime>13:09:00</ArrivalTime>
							<ArrivalDayOffset>0</ArrivalDayOffset>
							<DepartureTime>13:09:00</DepartureTime>
							<DepartureDayOffset>0</DepartureDayOffset>
						</TimetabledPassingTime>
						<TimetabledPassingTime>
							<ArrivalTime>13:12:00</ArrivalTime>
							<ArrivalDayOffset>0</ArrivalDayOffset>
							<DepartureTime>13:12:00</DepartureTime>
							<DepartureDayOffset>0</DepartureDayOffset>
						</TimetabledPassingTime>
						<TimetabledPassingTime>
							<ArrivalTime>13:14:00</ArrivalTime>
							<ArrivalDayOffset>0</ArrivalDayOffset>
							<DepartureTime>13:14:00</DepartureTime>
							<DepartureDayOffset>0</DepartureDayOffset>
						</TimetabledPassingTime>
						<TimetabledPassingTime>
							<ArrivalTime>13:15:00</ArrivalTime>
							<ArrivalDayOffset>0</ArrivalDayOffset>
							<DepartureTime>13:15:00</DepartureTime>
							<DepartureDayOffset>0</DepartureDayOffset>
						</TimetabledPassingTime>
					</passingTimes>
				</ServiceJourney>
			</members>
		</GeneralFrame>
	</dataObjects>
</PublicationDelivery>